{
  "number": 93,
  "name": "سُورَةُ الضُّحَىٰ",
  "englishName": "Ad-Dhuhaa",
  "englishNameTranslation": "The Morning Hours",
  "revelationType": "Meccan",
  "ayahs": [
    {
      "number": 6080,
      "numberInSurah": 1,
      "arabic": "بِسْمِ ٱللَّهِ ٱلرَّحْمَٰنِ ٱلرَّحِيمِ وَٱلضُّحَىٰ",
      "translations": {
        "en": "By the morning brightness",
        "ar": "أقسم الله بوقت الضحى، والمراد به النهار كله، وبالليل إذا سكن بالخلق واشتد ظلامه. ويقسم الله بما يشاء من مخلوقاته، أما المخلوق فلا يجوز له أن يقسم بغير خالقه، فإن القسم بغير الله شرك. ما تركك -أيها النبي- ربك، وما أبغضك بإبطاء الوحي عنك.",
        "ku": "سوێند به چێشته‌نگاو (کاتێك خۆر به‌رز ده‌بێته‌وه‌و کاتی جوڵه‌و چالاکیه‌)."
      },
      "juz": 30,
      "page": 596,
      "sajda": false
    },
    {
      "number": 6081,
      "numberInSurah": 2,
      "arabic": "وَٱلَّيْلِ إِذَا سَجَىٰ",
      "translations": {
        "en": "And [by] the night when it covers with darkness,",
        "ar": "أقسم الله بوقت الضحى، والمراد به النهار كله، وبالليل إذا سكن بالخلق واشتد ظلامه. ويقسم الله بما يشاء من مخلوقاته، أما المخلوق فلا يجوز له أن يقسم بغير خالقه، فإن القسم بغير الله شرك. ما تركك -أيها النبي- ربك، وما أبغضك بإبطاء الوحي عنك.",
        "ku": "سوێند به شه‌و کاتێك به‌تاریکیه‌که‌ی زه‌وی داده‌پۆشێت."
      },
      "juz": 30,
      "page": 596,
      "sajda": false
    },
    {
      "number": 6082,
      "numberInSurah": 3,
      "arabic": "مَا وَدَّعَكَ رَبُّكَ وَمَا قَلَىٰ",
      "translations": {
        "en": "Your Lord has not taken leave of you, [O Muhammad], nor has He detested [you].",
        "ar": "أقسم الله بوقت الضحى، والمراد به النهار كله، وبالليل إذا سكن بالخلق واشتد ظلامه. ويقسم الله بما يشاء من مخلوقاته، أما المخلوق فلا يجوز له أن يقسم بغير خالقه، فإن القسم بغير الله شرك. ما تركك -أيها النبي- ربك، وما أبغضك بإبطاء الوحي عنك.",
        "ku": "په‌روه‌ردگارت ده‌ستبه‌رداری تۆ نه‌بووه‌و وازی له تۆ نه‌هێناوه‌و خه‌شمی لێ نه‌گرتوویت (ماوه‌یه‌ك وه‌حی نه‌هات بۆ پێغه‌مبه‌ر صلی الله علیه وسلم کافرانی قوڕه‌یش وتیان، په‌روه‌ردگاری محمد وازی لێ هێناوه‌، ئیتر خوای گه‌وره به‌درۆی خسته‌وه‌)."
      },
      "juz": 30,
      "page": 596,
      "sajda": false
    },
    {
      "number": 6083,
      "numberInSurah": 4,
      "arabic": "وَلَلْءَاخِرَةُ خَيْرٌۭ لَّكَ مِنَ ٱلْأُولَىٰ",
      "translations": {
        "en": "And the Hereafter is better for you than the first [life].",
        "ar": "ولَلدَّار الآخرة خير لك من دار الدنيا، ولسوف يعطيك ربك -أيها النبي- مِن أنواع الإنعام في الآخرة، فترضى بذلك.",
        "ku": "بێگومان قیامه‌ت و دواڕۆژ چاکتره بۆ تۆ له دنیا."
      },
      "juz": 30,
      "page": 596,
      "sajda": false
    },
    {
      "number": 6084,
      "numberInSurah": 5,
      "arabic": "وَلَسَوْفَ يُعْطِيكَ رَبُّكَ فَتَرْضَىٰٓ",
      "translations": {
        "en": "And your Lord is going to give you, and you will be satisfied.",
        "ar": "ولَلدَّار الآخرة خير لك من دار الدنيا، ولسوف يعطيك ربك -أيها النبي- مِن أنواع الإنعام في الآخرة، فترضى بذلك.",
        "ku": "له ئاینده‌دا په‌روه‌ردگارت ئه‌وه‌نده نازو نیعمه‌تت پێده‌به‌خشێت که زۆر پێی ڕازی و خۆشنوود ده‌بیت."
      },
      "juz": 30,
      "page": 596,
      "sajda": false
    },
    {
      "number": 6085,
      "numberInSurah": 6,
      "arabic": "أَلَمْ يَجِدْكَ يَتِيمًۭا فَـَٔاوَىٰ",
      "translations": {
        "en": "Did He not find you an orphan and give [you] refuge?",
        "ar": "ألم يَجِدْك من قبلُ يتيمًا، فآواك ورعاك؟ ووجدك لا تدري ما الكتاب ولا الإيمان، فعلَّمك ما لم تكن تعلم، ووفقك لأحسن الأعمال؟ ووجدك فقيرًا، فساق لك رزقك، وأغنى نفسك بالقناعة والصبر؟",
        "ku": "ئایا په‌روه‌ردگارت نه‌یبینیت به هه‌تیوی و خێرا ده‌رووی لێکردیته‌وه و لانه‌ی بۆ سازاندیت و حه‌واندیتیه‌وه‌؟!"
      },
      "juz": 30,
      "page": 596,
      "sajda": false
    },
    {
      "number": 6086,
      "numberInSurah": 7,
      "arabic": "وَوَجَدَكَ ضَآلًّۭا فَهَدَىٰ",
      "translations": {
        "en": "And He found you lost and guided [you],",
        "ar": "ألم يَجِدْك من قبلُ يتيمًا، فآواك ورعاك؟ ووجدك لا تدري ما الكتاب ولا الإيمان، فعلَّمك ما لم تكن تعلم، ووفقك لأحسن الأعمال؟ ووجدك فقيرًا، فساق لك رزقك، وأغنى نفسك بالقناعة والصبر؟",
        "ku": "ئه‌ی سه‌رگه‌ردان نه‌بوویت و نه‌ت ده‌زانی چی بکه‌یت، هیدایه‌تی دایت و ڕێنموویی کردیت؟!"
      },
      "juz": 30,
      "page": 596,
      "sajda": false
    },
    {
      "number": 6087,
      "numberInSurah": 8,
      "arabic": "وَوَجَدَكَ عَآئِلًۭا فَأَغْنَىٰ",
      "translations": {
        "en": "And He found you poor and made [you] self-sufficient.",
        "ar": "ألم يَجِدْك من قبلُ يتيمًا، فآواك ورعاك؟ ووجدك لا تدري ما الكتاب ولا الإيمان، فعلَّمك ما لم تكن تعلم، ووفقك لأحسن الأعمال؟ ووجدك فقيرًا، فساق لك رزقك، وأغنى نفسك بالقناعة والصبر؟",
        "ku": "ئه‌ی نه‌یبینیت که هه‌ژارو نه‌داریت، جا ماڵ و سامانی پێبه‌خشیت و ده‌وڵه‌مه‌ندی کردیت و بێ نیازی کردیت؟!"
      },
      "juz": 30,
      "page": 596,
      "sajda": false
    },
    {
      "number": 6088,
      "numberInSurah": 9,
      "arabic": "فَأَمَّا ٱلْيَتِيمَ فَلَا تَقْهَرْ",
      "translations": {
        "en": "So as for the orphan, do not oppress [him].",
        "ar": "فأما اليتيم فلا تُسِئْ معاملته، وأما السائل فلا تزجره، بل أطعمه، واقض حاجته، وأما بنعمة ربك التي أسبغها عليك فتحدث بها.",
        "ku": "که‌واته تۆش (ئه‌ی پێغه‌مبه‌ر صلی الله علیه وسلم، ئه‌ی ئیماندار) هه‌تیو مه‌چه‌وسێنه‌ره‌وه‌و دڵی مه‌ڕه‌نجێنه‌."
      },
      "juz": 30,
      "page": 596,
      "sajda": false
    },
    {
      "number": 6089,
      "numberInSurah": 10,
      "arabic": "وَأَمَّا ٱلسَّآئِلَ فَلَا تَنْهَرْ",
      "translations": {
        "en": "And as for the petitioner, do not repel [him].",
        "ar": "فأما اليتيم فلا تُسِئْ معاملته، وأما السائل فلا تزجره، بل أطعمه، واقض حاجته، وأما بنعمة ربك التي أسبغها عليك فتحدث بها.",
        "ku": "هه‌ڵمه‌شاخێ به هه‌ژارو داماوو سواڵکه‌راندا."
      },
      "juz": 30,
      "page": 596,
      "sajda": false
    },
    {
      "number": 6090,
      "numberInSurah": 11,
      "arabic": "وَأَمَّا بِنِعْمَةِ رَبِّكَ فَحَدِّثْ",
      "translations": {
        "en": "But as for the favor of your Lord, report [it].",
        "ar": "فأما اليتيم فلا تُسِئْ معاملته، وأما السائل فلا تزجره، بل أطعمه، واقض حاجته، وأما بنعمة ربك التي أسبغها عليك فتحدث بها.",
        "ku": "(به‌ڵکو) ده‌رباره‌ی نازو نیعمه‌ته‌کانی په‌روه‌ردگارت هه‌میشه بدوێ و باسیان بکه له جێی خۆیاندا به‌کاریان بهێنه‌."
      },
      "juz": 30,
      "page": 596,
      "sajda": false
    }
  ]
}
