{
  "number": 98,
  "name": "سُورَةُ البَيِّنَةِ",
  "englishName": "Al-Bayyina",
  "englishNameTranslation": "The Evidence",
  "revelationType": "Medinan",
  "ayahs": [
    {
      "number": 6131,
      "numberInSurah": 1,
      "arabic": "بِسْمِ ٱللَّهِ ٱلرَّحْمَٰنِ ٱلرَّحِيمِ لَمْ يَكُنِ ٱلَّذِينَ كَفَرُوا۟ مِنْ أَهْلِ ٱلْكِتَٰبِ وَٱلْمُشْرِكِينَ مُنفَكِّينَ حَتَّىٰ تَأْتِيَهُمُ ٱلْبَيِّنَةُ",
      "translations": {
        "en": "Those who disbelieved among the People of the Scripture and the polytheists were not to be parted [from misbelief] until there came to them clear evidence -",
        "ar": "لم يكن الذين كفروا من اليهود والنصارى والمشركين تاركين كفرهم حتى تأتيهم العلامة التي وُعِدوا بها في الكتب السابقة.",
        "ku": "ئه‌وانه‌ی بێ باوه‌ڕ بوون له خاوه‌نی کتێبه‌کان له‌گه‌ڵ موشریك و هاوه‌ڵگه‌ران، وازیان له بیرو باوه‌ڕی خۆیان هێنا، هه‌تا به‌ڵگه‌و نیشانه‌ی ڕوون و ئاشکرایان بۆ نه‌هات (ده‌رباره‌ی دواهه‌مین پێغه‌مبه‌ر)."
      },
      "juz": 30,
      "page": 598,
      "sajda": false
    },
    {
      "number": 6132,
      "numberInSurah": 2,
      "arabic": "رَسُولٌۭ مِّنَ ٱللَّهِ يَتْلُوا۟ صُحُفًۭا مُّطَهَّرَةًۭ",
      "translations": {
        "en": "A Messenger from Allah, reciting purified scriptures",
        "ar": "وهي رسول الله محمد صلى الله عليه وسلم، يتلو قرآنًا في صحف مطهرة.",
        "ku": "(ئه‌ویش) پێغه‌مبه‌رێکه له‌لایه‌ن خواوه کتێب و نامه‌ی پاك و بێگه‌ردیان به‌سه‌ردا ده‌خوێنێته‌وه (که قورئانه‌)."
      },
      "juz": 30,
      "page": 598,
      "sajda": false
    },
    {
      "number": 6133,
      "numberInSurah": 3,
      "arabic": "فِيهَا كُتُبٌۭ قَيِّمَةٌۭ",
      "translations": {
        "en": "Within which are correct writings.",
        "ar": "في تلك الصحف أخبار صادقة وأوامر عادلة، تهدي إلى الحق وإلى صراط مستقيم.",
        "ku": "چه‌نده‌ها په‌یامی پڕ له ڕێنموویی به نرخی له توێدا هه‌یه‌."
      },
      "juz": 30,
      "page": 598,
      "sajda": false
    },
    {
      "number": 6134,
      "numberInSurah": 4,
      "arabic": "وَمَا تَفَرَّقَ ٱلَّذِينَ أُوتُوا۟ ٱلْكِتَٰبَ إِلَّا مِنۢ بَعْدِ مَا جَآءَتْهُمُ ٱلْبَيِّنَةُ",
      "translations": {
        "en": "Nor did those who were given the Scripture become divided until after there had come to them clear evidence.",
        "ar": "وما اختلف الذين أوتوا الكتاب من اليهود والنصارى في كون محمد صلى الله عليه وسلم رسولا حقًا؛ لما يجدونه من نعته في كتابهم، إلا مِن بعد ما تبينوا أنه النبي الذي وُعِدوا به في التوراة والإنجيل، فكانوا مجتمعين على صحة نبوته، فلما بُعِث جحدوها وتفرَّقوا.",
        "ku": "جا خاوه‌ن کتێبه‌کان ده‌سته ده‌سته‌و پارچه پارچه نه‌بوون، دوای ئه‌وه نه‌بێت که به‌ڵگه‌و نیشانه‌ی ئاشکرایان بۆ هات (ده‌رباره‌ی پێغه‌مبه‌رو قورئان)."
      },
      "juz": 30,
      "page": 598,
      "sajda": false
    },
    {
      "number": 6135,
      "numberInSurah": 5,
      "arabic": "وَمَآ أُمِرُوٓا۟ إِلَّا لِيَعْبُدُوا۟ ٱللَّهَ مُخْلِصِينَ لَهُ ٱلدِّينَ حُنَفَآءَ وَيُقِيمُوا۟ ٱلصَّلَوٰةَ وَيُؤْتُوا۟ ٱلزَّكَوٰةَ ۚ وَذَٰلِكَ دِينُ ٱلْقَيِّمَةِ",
      "translations": {
        "en": "And they were not commanded except to worship Allah, [being] sincere to Him in religion, inclining to truth, and to establish prayer and to give zakah. And that is the correct religion.",
        "ar": "وما أمروا في سائر الشرائع إلا ليعبدوا الله وحده قاصدين بعبادتهم وجهه، مائلين عن الشرك إلى الإيمان، ويقيموا الصلاة، ويُؤَدُّوا الزكاة، وذلك هو دين الاستقامة، وهو الإسلام.",
        "ku": "فه‌رمانیشیان پێنه‌درابوو جگه به‌وه‌ی که خواپه‌رستی بکه‌ن و به‌پاکی و دڵسۆزی و ملکه‌چی فه‌رمانبه‌رداری ئاین و به‌رنامه‌که بن و لابده‌ن له هه‌موو ئایینێك و ته‌نها پابه‌ندی ئایینی ئیسلام بن، نوێژیش به‌ڕێك و پێکی ئه‌نجام بده‌ن، زه‌کاتیش له ماڵ و سامانیان ده‌ربکه‌ن، ئه‌وه‌یه ئاینی نامه ڕاست و به‌نرخه‌کانی خوا."
      },
      "juz": 30,
      "page": 598,
      "sajda": false
    },
    {
      "number": 6136,
      "numberInSurah": 6,
      "arabic": "إِنَّ ٱلَّذِينَ كَفَرُوا۟ مِنْ أَهْلِ ٱلْكِتَٰبِ وَٱلْمُشْرِكِينَ فِى نَارِ جَهَنَّمَ خَٰلِدِينَ فِيهَآ ۚ أُو۟لَٰٓئِكَ هُمْ شَرُّ ٱلْبَرِيَّةِ",
      "translations": {
        "en": "Indeed, they who disbelieved among the People of the Scripture and the polytheists will be in the fire of Hell, abiding eternally therein. Those are the worst of creatures.",
        "ar": "إن الذين كفروا من اليهود والنصارى والمشركين عقابهم نار جهنم خالدين فيها، أولئك هم أشد الخليقة شرا.",
        "ku": "به‌ڕاستی ئه‌وانه‌ی بێ باوه‌ڕ بوون له خاوه‌ن کتێبه‌کان و موشریك و هاوه‌ڵگه‌ران ده‌خرێنه ناو ئاگری دۆزه‌خه‌وه‌و به نه‌مری تیایدا بۆ هه‌میشه ده‌مێننه‌وه‌، هه‌ر ئه‌وانه‌ن تاوانبارترین و خراپترینی خه‌ڵکانی سه‌رزه‌وی."
      },
      "juz": 30,
      "page": 598,
      "sajda": false
    },
    {
      "number": 6137,
      "numberInSurah": 7,
      "arabic": "إِنَّ ٱلَّذِينَ ءَامَنُوا۟ وَعَمِلُوا۟ ٱلصَّٰلِحَٰتِ أُو۟لَٰٓئِكَ هُمْ خَيْرُ ٱلْبَرِيَّةِ",
      "translations": {
        "en": "Indeed, they who have believed and done righteous deeds - those are the best of creatures.",
        "ar": "إن الذين صَدَّقوا الله واتبعوا رسوله وعملوا الصالحات، أولئك هم خير الخلق.",
        "ku": "بێگومان ئه‌وانه‌ی ئیمان و باوه‌ڕیان هێناوه‌و کارو کرده‌وه چاکه‌کانیان ئه‌نجامداوه‌، هه‌ر ئه‌وانه‌ن چاکترین و پاکترینی خه‌ڵکانی سه‌ر زه‌وی."
      },
      "juz": 30,
      "page": 598,
      "sajda": false
    },
    {
      "number": 6138,
      "numberInSurah": 8,
      "arabic": "جَزَآؤُهُمْ عِندَ رَبِّهِمْ جَنَّٰتُ عَدْنٍۢ تَجْرِى مِن تَحْتِهَا ٱلْأَنْهَٰرُ خَٰلِدِينَ فِيهَآ أَبَدًۭا ۖ رَّضِىَ ٱللَّهُ عَنْهُمْ وَرَضُوا۟ عَنْهُ ۚ ذَٰلِكَ لِمَنْ خَشِىَ رَبَّهُۥ",
      "translations": {
        "en": "Their reward with Allah will be gardens of perpetual residence beneath which rivers flow, wherein they will abide forever, Allah being pleased with them and they with Him. That is for whoever has feared his Lord.",
        "ar": "جزاؤهم عند ربهم يوم القيامة جنات إقامة واستقرار في منتهى الحسن، تجري من تحت قصورها الأنهار، خالدين فيها أبدًا، رضي الله عنهم فقبل أعمالهم الصالحة، ورضوا عنه بما أعدَّ لهم من أنواع الكرامات، ذلك الجزاء الحسن لمن خاف الله واجتنب معاصيه.",
        "ku": "پاداشتیان لای په‌روه‌ردگاریان به‌هه‌شتی پڕ له باخی چڕه (که کۆشك و ته‌لاره‌کان تیایدا ون بوون)، چه‌نده‌ها ڕووباریش به‌ژێر دره‌خت و به‌به‌رده‌م کۆشکه‌کانیدا ده‌ڕوات و له‌وێ ژیانی هه‌میشه‌یی و به‌رده‌وام بۆ هه‌تا هه‌تایی ده‌به‌نه سه‌ر، ئه‌وانه خوا ڕازیه لێیان، ئه‌وانیش له‌و ڕازین (چۆن ڕازی نابن ئه‌ی په‌روه‌ردگاری ئازیز، به‌ڕاستی نازانین به‌چ زمانێك سوپاسگوزارت بین) بێگومان ئه‌و ڕێزو قه‌دره بۆ ئه‌و که‌سه‌یه که له په‌روه‌ردگاری ترساوه‌و فه‌رمانه‌کانی به‌جێ هێناوه‌."
      },
      "juz": 30,
      "page": 599,
      "sajda": false
    }
  ]
}
